netbox_memory_input/__init__.py
netbox_memory_input/forms.py
netbox_memory_input-0.2.dist-info/METADATA
netbox_memory_input-0.2.dist-info/WHEEL
netbox_memory_input-0.2.dist-info/top_level.txt
netbox_memory_input-0.2.dist-info/RECORD
